evaltree/EvalTree.py
evaltree/__init__.py
evaltree/scripts/ComparingPartitions/.git/HEAD
evaltree/scripts/ComparingPartitions/.git/config
evaltree/scripts/ComparingPartitions/.git/description
evaltree/scripts/ComparingPartitions/.git/hooks/applypatch-msg.sample
evaltree/scripts/ComparingPartitions/.git/hooks/commit-msg.sample
evaltree/scripts/ComparingPartitions/.git/hooks/fsmonitor-watchman.sample
evaltree/scripts/ComparingPartitions/.git/hooks/post-update.sample
evaltree/scripts/ComparingPartitions/.git/hooks/pre-applypatch.sample
evaltree/scripts/ComparingPartitions/.git/hooks/pre-commit.sample
evaltree/scripts/ComparingPartitions/.git/hooks/pre-merge-commit.sample
evaltree/scripts/ComparingPartitions/.git/hooks/pre-push.sample
evaltree/scripts/ComparingPartitions/.git/hooks/pre-rebase.sample
evaltree/scripts/ComparingPartitions/.git/hooks/pre-receive.sample
evaltree/scripts/ComparingPartitions/.git/hooks/prepare-commit-msg.sample
evaltree/scripts/ComparingPartitions/.git/hooks/push-to-checkout.sample
evaltree/scripts/ComparingPartitions/.git/hooks/sendemail-validate.sample
evaltree/scripts/ComparingPartitions/.git/hooks/update.sample
evaltree/scripts/ComparingPartitions/.git/index
evaltree/scripts/ComparingPartitions/.git/info/exclude
evaltree/scripts/ComparingPartitions/.git/logs/HEAD
evaltree/scripts/ComparingPartitions/.git/logs/refs/heads/master
evaltree/scripts/ComparingPartitions/.git/logs/refs/remotes/origin/HEAD
evaltree/scripts/ComparingPartitions/.git/objects/pack/pack-b4866a13dc4806c75e665495ee6671b98a695802.idx
evaltree/scripts/ComparingPartitions/.git/objects/pack/pack-b4866a13dc4806c75e665495ee6671b98a695802.pack
evaltree/scripts/ComparingPartitions/.git/objects/pack/pack-b4866a13dc4806c75e665495ee6671b98a695802.rev
evaltree/scripts/ComparingPartitions/.git/packed-refs
evaltree/scripts/ComparingPartitions/.git/refs/heads/master
evaltree/scripts/ComparingPartitions/.git/refs/remotes/origin/HEAD
evaltree/scripts/ComparingPartitions/CP_demodata.txt
evaltree-1.0.0.dist-info/LICENSE
evaltree-1.0.0.dist-info/METADATA
evaltree-1.0.0.dist-info/WHEEL
evaltree-1.0.0.dist-info/entry_points.txt
evaltree-1.0.0.dist-info/RECORD
