Metadata-Version: 2.3
Name: evaltree
Version: 1.0.0
Summary: Toolbox for comparative clustering evaluation of WGS pipelines for bacterial routine surveillance
License: GPL-3.0-only
Requires-Python: >=3.10
Classifier: License :: OSI Approved :: GNU General Public License v3 (GPLv3)
Classifier: Programming Language :: Python :: 3
Classifier: Programming Language :: Python :: 3.10
Classifier: Programming Language :: Python :: 3.11
Classifier: Programming Language :: Python :: 3.12
Classifier: Programming Language :: Python :: 3.13
Requires-Dist: kaleido (<=0.2.1)
Requires-Dist: pandas (<=2.3.0)
Requires-Dist: plotly (<=5.24.1)
Requires-Dist: pytest (<=8.4.0)
Requires-Dist: scikit-learn (<=1.7.0)
Requires-Dist: scipy (<=1.15.2)
Requires-Dist: statsmodels (<=0.14.4)
Project-URL: repository, https://https://github.com/insapathogenomics/ACDTree
